{
  "region": "North",
  "province": "Hanoi",
  "date": "2026-01-01",
  "prizes": {
    "special": [
      "57068"
    ],
    "first": [
      "42408"
    ],
    "second": [
      "08125",
      "48752"
    ],
    "third": [
      "04842",
      "46588",
      "59776",
      "80235",
      "87572",
      "95131"
    ],
    "fourth": [
      "1801",
      "3634",
      "3976",
      "6138"
    ],
    "fifth": [
      "4363",
      "5253",
      "7217",
      "7525",
      "7828",
      "8796"
    ],
    "sixth": [
      "253",
      "617",
      "731"
    ],
    "seventh": [
      "25",
      "67",
      "69",
      "91"
    ]
  },
  "source": "minhngoc",
  "consensusSources": [
    "minhngoc",
    "xoso",
    "xosodaiphat"
  ]
}
